{
    "author": "Lauren Bastide",
    "copyright": "Lauren Bastide",
    "creator": "Lauren Bastide",
    "description": "<p>Deux fois par mois, au micro de Lauren Bastide, \u00e9crivaines, artistes, chercheuses et militantes se racontent et prennent le pouls des luttes f\u00e9ministes et antiracistes contemporaines.\u00a0</p><p>Depuis 2016, la journaliste re\u00e7oit dans La Poudre des femmes artistes, militantes ou politiques pour des conversations intimes et profondes qui ont passionn\u00e9 de millions d\u2019auditeurices. Ces r\u00e9cits, enrichis de documentaires \u00e9v\u00e9nementiels, de tables rondes, et d\u2019analyses par les plus grandes expertes des luttes pour les droits des femmes, en France et dans le monde, forment un tableau captivant de la soci\u00e9t\u00e9 \u00e0 l\u2019heure de la r\u00e9volution #MeToo.\u00a0</p><p>La Poudre was created by journalist and feminist activist Lauren Bastide, co-founder of Nouvelles Ecoutes studio, to offer women a safe space to express themselves. In a one-hour long, in-depth conversation, inspirational women artists, activists, scientists and politics talk about themselves, their path and struggles, but also about the incredible times we are living for women\u2019s rights. Many episodes of La Poudre have been recorded or dubbed into English. Search for the \ud83c\uddec\ud83c\udde7 !</p>",
    "feedUrl": "https://anchor.fm/s/6a2cdc64/podcast/rss",
    "generator": "Anchor Podcasts",
    "image": {
        "link": "https://podcasters.spotify.com/pod/show/lauren-bastide",
        "title": "La Poudre",
        "url": "https://d3t3ozftmdmh3i.cloudfront.net/production/podcast_uploaded_nologo/17713249/17713249-1632211174146-8cc0954b36cf3.jpg"
    },
    "items": [
        {
            "content": "<p>Nous sommes tr\u00e8s heureuses de vous annoncer qu'\u00e0 partir du 20 octobre, La Poudre s\u2019\u00e9coutera en exclusivit\u00e9 sur Spotify.<br>\nSi vous ne voulez pas perdre une miette de la saison 6, nous vous recommandons de vous abonner au flux de La Poudre sur l\u2019application Spotify, dans la rubrique podcast. Bien s\u00fbr, La Poudre reste accessible \u00e0 toustes gratuitement, il suffit de se cr\u00e9er un compte. Et pour le reste, rien ne va changer ! La Poudre va rester le podcast intime, passionnant et engag\u00e9 que vous aimez.<br>\nNous comptons sur vous pour nous suivre chez Spotify, cette saison va receler d\u2019\u00e9pisodes plus explosifs que jamais. Rendez-vous le 20 octobre !</p>\n",
            "contentSnippet": "Nous sommes tr\u00e8s heureuses de vous annoncer qu'\u00e0 partir du 20 octobre, La Poudre s\u2019\u00e9coutera en exclusivit\u00e9 sur Spotify.\nSi vous ne voulez pas perdre une miette de la saison 6, nous vous recommandons de vous abonner au flux de La Poudre sur l\u2019application Spotify, dans la rubrique podcast. Bien s\u00fbr, La Poudre reste accessible \u00e0 toustes gratuitement, il suffit de se cr\u00e9er un compte. Et pour le reste, rien ne va changer ! La Poudre va rester le podcast intime, passionnant et engag\u00e9 que vous aimez.\nNous comptons sur vous pour nous suivre chez Spotify, cette saison va receler d\u2019\u00e9pisodes plus explosifs que jamais. Rendez-vous le 20 octobre !",
            "creator": "Lauren Bastide",
            "dc:creator": "Lauren Bastide",
            "enclosure": {
                "length": "2487680",
                "type": "audio/mpeg",
                "url": "https://anchor.fm/s/6a2cdc64/podcast/play/40557867/https%3A%2F%2Fd3ctxlq1ktw2nl.cloudfront.net%2Fstaging%2F2021-8-20%2Fad197d31-e7ee-a74d-25dc-a933689047fc.mp3"
            },
            "guid": "4e4eb36d-ea73-406c-859b-80576161df51",
            "isoDate": "2021-09-21T07:58:00.000Z",
            "itunes": {
                "duration": "00:01:17",
                "episodeType": "full",
                "explicit": "No",
                "image": "https://d3t3ozftmdmh3i.cloudfront.net/production/podcast_uploaded_episode400/17713249/17713249-1632153503197-38a5d91abfb3b.jpg",
                "summary": "<p>Nous sommes tr\u00e8s heureuses de vous annoncer qu'\u00e0 partir du 20 octobre, La Poudre s\u2019\u00e9coutera en exclusivit\u00e9 sur Spotify.<br>\nSi vous ne voulez pas perdre une miette de la saison 6, nous vous recommandons de vous abonner au flux de La Poudre sur l\u2019application Spotify, dans la rubrique podcast. Bien s\u00fbr, La Poudre reste accessible \u00e0 toustes gratuitement, il suffit de se cr\u00e9er un compte. Et pour le reste, rien ne va changer ! La Poudre va rester le podcast intime, passionnant et engag\u00e9 que vous aimez.<br>\nNous comptons sur vous pour nous suivre chez Spotify, cette saison va receler d\u2019\u00e9pisodes plus explosifs que jamais. Rendez-vous le 20 octobre !</p>\n"
            },
            "link": "https://podcasters.spotify.com/pod/show/lauren-bastide/episodes/La-Poudre-passe-chez-Spotify-e17k7rb",
            "pubDate": "Tue, 21 Sep 2021 07:58:00 GMT",
            "title": "La Poudre passe chez Spotify",
            "entities": {
                "CARDINAL": [
                    "20",
                    "6",
                    "20"
                ],
                "PERSON": [
                    "La Poudre s\u2019\u00e9coutera",
                    "miette de la saison",
                    "Bien s\u00fbr"
                ],
                "GPE": [
                    "Spotify",
                    "Si",
                    "Spotify"
                ],
                "PRODUCT": [
                    "Spotify"
                ],
                "ORG": [
                    "dans la rubrique",
                    "La Poudre",
                    "cr\u00e9er un compte"
                ],
                "FAC": [
                    "La Poudre"
                ]
            }
        },
        {
            "content": "La Poudre essaime depuis 6 saisons, et rec\u00e8le d\u2019interviews passionnantes avec des femmes artistes, militantes, politiques, d\u2019analyses men\u00e9es avec les plus grandes chercheur\u00b7euse\u00b7s contemporain\u00b7e\u00b7s en \u00e9tudes de genre, de tables rondes s\u2019attaquant au monde d\u2019aujourd\u2019hui et de documentaires \u00e9v\u00e9nementiels sur les luttes pour les droits des femmes.\nSi cet \u00e9pisode vous a plu, vous pourrez retrouver tous les (nombreux) autres sur Spotify !\n\n\nLes philosophes et chercheuses Manon Garcia, Sandra Laugier et \u00c9l\u00e9onore L\u00e9pinard sont les invit\u00e9es du 100e \u00e9pisode de La Poudre, enregistr\u00e9 aux Rencontres Philosophiques de Monaco le 18 juin 2021. Avec Lauren Bastide, elles ont parl\u00e9 des r\u00e9sistances contre la pens\u00e9e f\u00e9ministe, beaucoup plus parl\u00e9 de taches m\u00e9nag\u00e8res que pr\u00e9vu, de sexe et de notre ras-le-bol de ne pas \u00eatre \u00e9cout\u00e9es, bref, elles ont beaucoup parl\u00e9 des hommes.\n\n\nL\u2019\u00e9dito de Lauren :\n\nBon en vrai je mens, c\u2019est pas l\u2019\u00e9pisode 100. Enfin si, c\u2019est l\u2019\u00e9pisode 100 parce qu\u2019il arrive juste apr\u00e8s l\u2019\u00e9pisode 99. Mais c\u2019est en fait le 139e \u00e9pisode mis en ligne, parce que pendant les quatre premi\u00e8res saisons, on ne num\u00e9rotait pas les tables rondes, on les appelait \u201c\u00e9pisode bonus\u201d. Enfin bref, c\u2019est notre cuisine interne \u00e7a vous regarde pas vraiment, mais c\u2019est int\u00e9ressant parce que le fait que j\u2019appelle cet \u00e9pisode \u201cl\u2019\u00e9pisode 100\u201d, \u00e7a raconte aussi un peu ce qu\u2019est la pens\u00e9e f\u00e9ministe. Si si, \u00e7a raconte le fait que chaque savoir, chaque d\u00e9compte, chaque nomination, chaque concept est fondamentalement situ\u00e9. Chaque nom, chaque chiffre, chaque pens\u00e9e est complexe, et imbib\u00e9e de l\u2019identit\u00e9 de celle ou de celui qui en est l\u2019auteur ou l\u2019autrice. Pour r\u00e9sumer, d\u2019un point de vue universaliste cet \u00e9pisode n\u2019est pas l\u2019\u00e9pisode 100, mais de mon point de vue \u00e0 moi \u2013 le seul qui compte du coup puisque ce podcast est mon espace et\u00a0 un peu ma narration \u2013, ben si, en fait, c\u2019est l\u2019\u00e9pisode 100. Je m\u2019envole un peu l\u00e0, je suis d\u00e9sol\u00e9e. J\u2019arr\u00eate pas de m\u2019envoler comme \u00e7a depuis que je me penche sur la philosophie. C\u2019est fabuleux, la philosophie. C\u2019est presque aussi chouette que la sociologie. C\u2019est pour cela que lorsque Charlotte Casiraghi m\u2019a propos\u00e9 d\u2019animer une table ronde f\u00e9ministe aux Rencontres Philosophiques de Monaco, bah j\u2019ai saut\u00e9 de joie. J\u2019ai r\u00e9uni autour de la table trois penseuses f\u00e9ministes, avec l\u2019id\u00e9e qu\u2019on allait toutes ensemble r\u00e9ussir \u00e0 penser des futurs f\u00e9ministes, les futurs f\u00e9ministes, et \u00e0 d\u00e9crire ce \u00e0 quoi pourrait ressembler une soci\u00e9t\u00e9 v\u00e9ritablement \u00e9galitaire, v\u00e9ritablement juste, v\u00e9ritablement libre. C\u2019est le dernier \u00e9pisode de la saison 5 de La Poudre. Une saison qui a \u00e9t\u00e9 riche en savoirs, en complexit\u00e9 et en espoir, et que je vous remercie du fond du c\u0153ur d\u2019avoir suivi. Pour continuer de suivre les aventures de La Poudre \u00e0 la rentr\u00e9e, je vous invite fort \u00e0 suivre La Poudre sur les r\u00e9seaux sociaux, notamment Instagram o\u00f9 on vous tiendra au courant de la suite des \u00e9v\u00e9nements qui va peut-\u00eatre vous surprendre. En attendant, place \u00e0 la philosophie ! Cet \u00e9pisode est d\u00e9licieusement long, r\u00e9galez-vous bien.\u00a0\n\n\n\n\nR\u00e9sum\u00e9 de l\u2019\u00e9pisode :\n\nAlors que depuis plus d\u2019un an, l\u2019incertitude r\u00e8gne en ma\u00eetresse et que le climat politique se raidit, comment penser le futur ? Comment opter entre utopie et dystopie ? Lauren Bastide a tendu son micro \u00e0 trois immenses penseuses pour tenter d\u2019apporter quelques r\u00e9ponses : les philosophes Manon Garcia et Sandra Laugier ainsi que la sociologue \u00c9l\u00e9onore L\u00e9pinard. Ensemble, elles se penchent sur ce que le f\u00e9minisme peut pour la philosophie et inversement (09:25), mais aussi en quoi il est positif de voir la place qu\u2019il prend dans les disciplines telles que la philosophie dans ces temps o\u00f9 toute une partie des sciences sociales est menac\u00e9e (19:37). Elles explorent en quoi la pens\u00e9e du care ou encore l\u2019\u00e9cof\u00e9minisme pourraient apporter des \u00e9l\u00e9ments concrets pour penser des politiques publiques plus \u00e9galitaires et durables (32:33) mais constatent aussi la pr\u00e9sence de nombreux obstacles et r\u00e9sistances contre ces futurs p\n",
            "contentSnippet": "La Poudre essaime depuis 6 saisons, et rec\u00e8le d\u2019interviews passionnantes avec des femmes artistes, militantes, politiques, d\u2019analyses men\u00e9es avec les plus grandes chercheur\u00b7euse\u00b7s contemporain\u00b7e\u00b7s en \u00e9tudes de genre, de tables rondes s\u2019attaquant au monde d\u2019aujourd\u2019hui et de documentaires \u00e9v\u00e9nementiels sur les luttes pour les droits des femmes.\nSi cet \u00e9pisode vous a plu, vous pourrez retrouver tous les (nombreux) autres sur Spotify !\n\n\nLes philosophes et chercheuses Manon Garcia, Sandra Laugier et \u00c9l\u00e9onore L\u00e9pinard sont les invit\u00e9es du 100e \u00e9pisode de La Poudre, enregistr\u00e9 aux Rencontres Philosophiques de Monaco le 18 juin 2021. Avec Lauren Bastide, elles ont parl\u00e9 des r\u00e9sistances contre la pens\u00e9e f\u00e9ministe, beaucoup plus parl\u00e9 de taches m\u00e9nag\u00e8res que pr\u00e9vu, de sexe et de notre ras-le-bol de ne pas \u00eatre \u00e9cout\u00e9es, bref, elles ont beaucoup parl\u00e9 des hommes.\n\n\nL\u2019\u00e9dito de Lauren :\n\nBon en vrai je mens, c\u2019est pas l\u2019\u00e9pisode 100. Enfin si, c\u2019est l\u2019\u00e9pisode 100 parce qu\u2019il arrive juste apr\u00e8s l\u2019\u00e9pisode 99. Mais c\u2019est en fait le 139e \u00e9pisode mis en ligne, parce que pendant les quatre premi\u00e8res saisons, on ne num\u00e9rotait pas les tables rondes, on les appelait \u201c\u00e9pisode bonus\u201d. Enfin bref, c\u2019est notre cuisine interne \u00e7a vous regarde pas vraiment, mais c\u2019est int\u00e9ressant parce que le fait que j\u2019appelle cet \u00e9pisode \u201cl\u2019\u00e9pisode 100\u201d, \u00e7a raconte aussi un peu ce qu\u2019est la pens\u00e9e f\u00e9ministe. Si si, \u00e7a raconte le fait que chaque savoir, chaque d\u00e9compte, chaque nomination, chaque concept est fondamentalement situ\u00e9. Chaque nom, chaque chiffre, chaque pens\u00e9e est complexe, et imbib\u00e9e de l\u2019identit\u00e9 de celle ou de celui qui en est l\u2019auteur ou l\u2019autrice. Pour r\u00e9sumer, d\u2019un point de vue universaliste cet \u00e9pisode n\u2019est pas l\u2019\u00e9pisode 100, mais de mon point de vue \u00e0 moi \u2013 le seul qui compte du coup puisque ce podcast est mon espace et\u00a0 un peu ma narration \u2013, ben si, en fait, c\u2019est l\u2019\u00e9pisode 100. Je m\u2019envole un peu l\u00e0, je suis d\u00e9sol\u00e9e. J\u2019arr\u00eate pas de m\u2019envoler comme \u00e7a depuis que je me penche sur la philosophie. C\u2019est fabuleux, la philosophie. C\u2019est presque aussi chouette que la sociologie. C\u2019est pour cela que lorsque Charlotte Casiraghi m\u2019a propos\u00e9 d\u2019animer une table ronde f\u00e9ministe aux Rencontres Philosophiques de Monaco, bah j\u2019ai saut\u00e9 de joie. J\u2019ai r\u00e9uni autour de la table trois penseuses f\u00e9ministes, avec l\u2019id\u00e9e qu\u2019on allait toutes ensemble r\u00e9ussir \u00e0 penser des futurs f\u00e9ministes, les futurs f\u00e9ministes, et \u00e0 d\u00e9crire ce \u00e0 quoi pourrait ressembler une soci\u00e9t\u00e9 v\u00e9ritablement \u00e9galitaire, v\u00e9ritablement juste, v\u00e9ritablement libre. C\u2019est le dernier \u00e9pisode de la saison 5 de La Poudre. Une saison qui a \u00e9t\u00e9 riche en savoirs, en complexit\u00e9 et en espoir, et que je vous remercie du fond du c\u0153ur d\u2019avoir suivi. Pour continuer de suivre les aventures de La Poudre \u00e0 la rentr\u00e9e, je vous invite fort \u00e0 suivre La Poudre sur les r\u00e9seaux sociaux, notamment Instagram o\u00f9 on vous tiendra au courant de la suite des \u00e9v\u00e9nements qui va peut-\u00eatre vous surprendre. En attendant, place \u00e0 la philosophie ! Cet \u00e9pisode est d\u00e9licieusement long, r\u00e9galez-vous bien.\u00a0\n\n\n\n\nR\u00e9sum\u00e9 de l\u2019\u00e9pisode :\n\nAlors que depuis plus d\u2019un an, l\u2019incertitude r\u00e8gne en ma\u00eetresse et que le climat politique se raidit, comment penser le futur ? Comment opter entre utopie et dystopie ? Lauren Bastide a tendu son micro \u00e0 trois immenses penseuses pour tenter d\u2019apporter quelques r\u00e9ponses : les philosophes Manon Garcia et Sandra Laugier ainsi que la sociologue \u00c9l\u00e9onore L\u00e9pinard. Ensemble, elles se penchent sur ce que le f\u00e9minisme peut pour la philosophie et inversement (09:25), mais aussi en quoi il est positif de voir la place qu\u2019il prend dans les disciplines telles que la philosophie dans ces temps o\u00f9 toute une partie des sciences sociales est menac\u00e9e (19:37). Elles explorent en quoi la pens\u00e9e du care ou encore l\u2019\u00e9cof\u00e9minisme pourraient apporter des \u00e9l\u00e9ments concrets pour penser des politiques publiques plus \u00e9galitaires et durables (32:33) mais constatent aussi la pr\u00e9sence de nombreux obstacles et r\u00e9sistances contre ces futurs p",
            "creator": "Lauren Bastide",
            "dc:creator": "Lauren Bastide",
            "enclosure": {
                "length": "83348156",
                "type": "audio/x-m4a",
                "url": "https://anchor.fm/s/6a2cdc64/podcast/play/39764441/https%3A%2F%2Fd3ctxlq1ktw2nl.cloudfront.net%2Fstaging%2F2021-10-19%2F058daee44561f86b4f09bf8ac3f367fe.m4a"
            },
            "guid": "gid://art19-episode-locator/V0/-rhaUvtiHRyZkxOTqbBIH_E93wIb-bi-C29oF_H9p-g",
            "isoDate": "2021-07-15T04:00:00.000Z",
            "itunes": {
                "duration": "01:25:53",
                "episodeType": "full",
                "explicit": "No",
                "image": "https://d3t3ozftmdmh3i.cloudfront.net/staging/podcast_uploaded_episode400/17713249/a24bae3738df7513.jpeg",
                "summary": "La Poudre essaime depuis 6 saisons, et rec\u00e8le d\u2019interviews passionnantes avec des femmes artistes, militantes, politiques, d\u2019analyses men\u00e9es avec les plus grandes chercheur\u00b7euse\u00b7s contemporain\u00b7e\u00b7s en \u00e9tudes de genre, de tables rondes s\u2019attaquant au monde d\u2019aujourd\u2019hui et de documentaires \u00e9v\u00e9nementiels sur les luttes pour les droits des femmes.\nSi cet \u00e9pisode vous a plu, vous pourrez retrouver tous les (nombreux) autres sur Spotify !\n\n\nLes philosophes et chercheuses Manon Garcia, Sandra Laugier et \u00c9l\u00e9onore L\u00e9pinard sont les invit\u00e9es du 100e \u00e9pisode de La Poudre, enregistr\u00e9 aux Rencontres Philosophiques de Monaco le 18 juin 2021. Avec Lauren Bastide, elles ont parl\u00e9 des r\u00e9sistances contre la pens\u00e9e f\u00e9ministe, beaucoup plus parl\u00e9 de taches m\u00e9nag\u00e8res que pr\u00e9vu, de sexe et de notre ras-le-bol de ne pas \u00eatre \u00e9cout\u00e9es, bref, elles ont beaucoup parl\u00e9 des hommes.\n\n\nL\u2019\u00e9dito de Lauren :\n\nBon en vrai je mens, c\u2019est pas l\u2019\u00e9pisode 100. Enfin si, c\u2019est l\u2019\u00e9pisode 100 parce qu\u2019il arrive juste apr\u00e8s l\u2019\u00e9pisode 99. Mais c\u2019est en fait le 139e \u00e9pisode mis en ligne, parce que pendant les quatre premi\u00e8res saisons, on ne num\u00e9rotait pas les tables rondes, on les appelait \u201c\u00e9pisode bonus\u201d. Enfin bref, c\u2019est notre cuisine interne \u00e7a vous regarde pas vraiment, mais c\u2019est int\u00e9ressant parce que le fait que j\u2019appelle cet \u00e9pisode \u201cl\u2019\u00e9pisode 100\u201d, \u00e7a raconte aussi un peu ce qu\u2019est la pens\u00e9e f\u00e9ministe. Si si, \u00e7a raconte le fait que chaque savoir, chaque d\u00e9compte, chaque nomination, chaque concept est fondamentalement situ\u00e9. Chaque nom, chaque chiffre, chaque pens\u00e9e est complexe, et imbib\u00e9e de l\u2019identit\u00e9 de celle ou de celui qui en est l\u2019auteur ou l\u2019autrice. Pour r\u00e9sumer, d\u2019un point de vue universaliste cet \u00e9pisode n\u2019est pas l\u2019\u00e9pisode 100, mais de mon point de vue \u00e0 moi \u2013 le seul qui compte du coup puisque ce podcast est mon espace et\u00a0 un peu ma narration \u2013, ben si, en fait, c\u2019est l\u2019\u00e9pisode 100. Je m\u2019envole un peu l\u00e0, je suis d\u00e9sol\u00e9e. J\u2019arr\u00eate pas de m\u2019envoler comme \u00e7a depuis que je me penche sur la philosophie. C\u2019est fabuleux, la philosophie. C\u2019est presque aussi chouette que la sociologie. C\u2019est pour cela que lorsque Charlotte Casiraghi m\u2019a propos\u00e9 d\u2019animer une table ronde f\u00e9ministe aux Rencontres Philosophiques de Monaco, bah j\u2019ai saut\u00e9 de joie. J\u2019ai r\u00e9uni autour de la table trois penseuses f\u00e9ministes, avec l\u2019id\u00e9e qu\u2019on allait toutes ensemble r\u00e9ussir \u00e0 penser des futurs f\u00e9ministes, les futurs f\u00e9ministes, et \u00e0 d\u00e9crire ce \u00e0 quoi pourrait ressembler une soci\u00e9t\u00e9 v\u00e9ritablement \u00e9galitaire, v\u00e9ritablement juste, v\u00e9ritablement libre. C\u2019est le dernier \u00e9pisode de la saison 5 de La Poudre. Une saison qui a \u00e9t\u00e9 riche en savoirs, en complexit\u00e9 et en espoir, et que je vous remercie du fond du c\u0153ur d\u2019avoir suivi. Pour continuer de suivre les aventures de La Poudre \u00e0 la rentr\u00e9e, je vous invite fort \u00e0 suivre La Poudre sur les r\u00e9seaux sociaux, notamment Instagram o\u00f9 on vous tiendra au courant de la suite des \u00e9v\u00e9nements qui va peut-\u00eatre vous surprendre. En attendant, place \u00e0 la philosophie ! Cet \u00e9pisode est d\u00e9licieusement long, r\u00e9galez-vous bien.\u00a0\n\n\n\n\nR\u00e9sum\u00e9 de l\u2019\u00e9pisode :\n\nAlors que depuis plus d\u2019un an, l\u2019incertitude r\u00e8gne en ma\u00eetresse et que le climat politique se raidit, comment penser le futur ? Comment opter entre utopie et dystopie ? Lauren Bastide a tendu son micro \u00e0 trois immenses penseuses pour tenter d\u2019apporter quelques r\u00e9ponses : les philosophes Manon Garcia et Sandra Laugier ainsi que la sociologue \u00c9l\u00e9onore L\u00e9pinard. Ensemble, elles se penchent sur ce que le f\u00e9minisme peut pour la philosophie et inversement (09:25), mais aussi en quoi il est positif de voir la place qu\u2019il prend dans les disciplines telles que la philosophie dans ces temps o\u00f9 toute une partie des sciences sociales est menac\u00e9e (19:37). Elles explorent en quoi la pens\u00e9e du care ou encore l\u2019\u00e9cof\u00e9minisme pourraient apporter des \u00e9l\u00e9ments concrets pour penser des politiques publiques plus \u00e9galitaires et durables (32:33) mais constatent aussi la pr\u00e9sence de nombreux obstacles et r\u00e9sistances contre ces futurs p\n"
            },
            "link": "https://podcasters.spotify.com/pod/show/lauren-bastide/episodes/pisode-100---Penser-les-futurs-fministes-e16s10p",
            "pubDate": "Thu, 15 Jul 2021 04:00:00 GMT",
            "title": "\u00c9pisode 100 - Penser les futurs f\u00e9ministes",
            "entities": {
                "CARDINAL": [
                    "6",
                    "100e",
                    "18",
                    "100",
                    "100",
                    "99",
                    "100",
                    "100"
                ],
                "PERSON": [
                    "Si cet \u00e9pisode",
                    "Manon Garcia",
                    "Sandra Laugier",
                    "Avec Lauren Bastide",
                    "L\u2019\u00e9dito de Lauren",
                    "juste apr\u00e8s",
                    "Mais",
                    "chaque chiffre",
                    "imbib\u00e9e de l\u2019identit\u00e9 de celle",
                    "ben si",
                    "Je m\u2019envole un peu l\u00e0",
                    "J\u2019arr\u00eate pas de m\u2019envoler",
                    "aussi chouette",
                    "Charlotte Casiraghi",
                    "autour de la",
                    "fond du c\u0153ur d\u2019avoir suivi",
                    "de La Poudre",
                    "r\u00e9seaux sociaux",
                    "Instagram",
                    "courant de la",
                    "R\u00e9sum\u00e9 de l\u2019\u00e9pisode :",
                    "Lauren Bastide",
                    "Sandra Laugier",
                    "\u00c9l\u00e9onore L\u00e9pinard",
                    "mais aussi",
                    "menac\u00e9e",
                    "mais constatent"
                ],
                "FAC": [
                    "Spotify",
                    "La Poudre",
                    "Manon Garcia"
                ],
                "ORG": [
                    "Rencontres Philosophiques de Monaco",
                    "qu\u2019il",
                    "un",
                    "Chaque",
                    "l\u2019auteur",
                    "un",
                    "Rencontres Philosophiques de Monaco",
                    "j\u2019ai saut\u00e9 de joie",
                    "qu\u2019il"
                ],
                "DATE": [
                    "2021"
                ],
                "GPE": [
                    "bref",
                    "la rentr\u00e9e",
                    "la pens\u00e9e"
                ],
                "PRODUCT": [
                    "139e",
                    "peu ce",
                    "qu\u2019on allait"
                ],
                "NORP": [
                    "fabuleux",
                    "dans",
                    "dans"
                ],
                "TIME": [
                    "09:25"
                ]
            }
        },
        {
            "content": "<p>La Poudre essaime depuis 6 saisons, et rec\u00e8le d\u2019interviews passionnantes avec des femmes artistes, militantes, politiques, d\u2019analyses men\u00e9es avec les plus grandes chercheur\u00b7euse\u00b7s contemporain\u00b7e\u00b7s en \u00e9tudes de genre, de tables rondes s\u2019attaquant au monde d\u2019aujourd\u2019hui et de documentaires \u00e9v\u00e9nementiels sur les luttes pour les droits des femmes. Si cet \u00e9pisode vous a plu, vous pourrez retrouver tous les (nombreux) autres sur Spotify !</p>\n<p>Dans ce tout premier \u00e9pisode de La Poudre, Rebecca Zlotowski se livre au micro de Lauren Bastide (@LaurenBastide), dans l\u2019intimit\u00e9 d'une chambre d\u2019h\u00f4tel. R\u00e9compens\u00e9e du Prix Louis-Delluc du premier film pour&nbsp;\"Belle Epine\" (2011) puis du Prix Fran\u00e7ois Chalais dans la s\u00e9lection Un Certain Regard au&nbsp;Festival de Cannes pour \"Grand Central\" (2013), avec L\u00e9a Seydoux en t\u00eate d'affiche,&nbsp;Rebecca Zlotowski est consid\u00e9r\u00e9e comme l'une des r\u00e9alisatrices les plus talentueuses de sa g\u00e9n\u00e9ration. Son nouveau film, \"Planetarium\" avec Natalie Portman et Lily-Rose Depp, est sorti en salle le 16 novembre 2016. Rebecca Zlotowski \u00e9voque avec Lauren Bastide&nbsp;les \u00e9pisodes de sa vie et de sa carri\u00e8re qui ont fa\u00e7onn\u00e9 sa construction en tant que femme. Son enfance, la mort de sa m\u00e8re et sa pubert\u00e9 (05.36), son passage d'une agr\u00e9gation de lettres au m\u00e9tier de r\u00e9alisatrice (19:03), le sexisme dans le&nbsp;cin\u00e9ma fran\u00e7ais (24:30), ses rapports avec L\u00e9a Seydoux et Lily-Rose Depp (29:22) et le caract\u00e8re forc\u00e9ment pr\u00e9dateur&nbsp;du m\u00e9tier de metteur en sc\u00e8ne (33:36).&nbsp; La Poudre&nbsp;est une production Nouvelles \u00c9coutes R\u00e9alisation et g\u00e9n\u00e9rique : Aurore Meyer-Mahieu. Mixage : Zaki Allal. Assistante de production : Zisla Tortello.&nbsp; ------ Cet \u00e9pisode 1 de La Poudre, enregistr\u00e9 \u00e0 l\u2019H\u00f4tel Providence, est rendu possible gr\u00e2ce au soutien des micros Blue Microphones. ------ vcfr3b5x See Privacy Policy at https://art19.com/privacy and California Privacy Notice at https://art19.com/privacy#do-not-sell-my-info.</p>\n",
            "contentSnippet": "La Poudre essaime depuis 6 saisons, et rec\u00e8le d\u2019interviews passionnantes avec des femmes artistes, militantes, politiques, d\u2019analyses men\u00e9es avec les plus grandes chercheur\u00b7euse\u00b7s contemporain\u00b7e\u00b7s en \u00e9tudes de genre, de tables rondes s\u2019attaquant au monde d\u2019aujourd\u2019hui et de documentaires \u00e9v\u00e9nementiels sur les luttes pour les droits des femmes. Si cet \u00e9pisode vous a plu, vous pourrez retrouver tous les (nombreux) autres sur Spotify !\nDans ce tout premier \u00e9pisode de La Poudre, Rebecca Zlotowski se livre au micro de Lauren Bastide (@LaurenBastide), dans l\u2019intimit\u00e9 d'une chambre d\u2019h\u00f4tel. R\u00e9compens\u00e9e du Prix Louis-Delluc du premier film pour\u00a0\"Belle Epine\" (2011) puis du Prix Fran\u00e7ois Chalais dans la s\u00e9lection Un Certain Regard au\u00a0Festival de Cannes pour \"Grand Central\" (2013), avec L\u00e9a Seydoux en t\u00eate d'affiche,\u00a0Rebecca Zlotowski est consid\u00e9r\u00e9e comme l'une des r\u00e9alisatrices les plus talentueuses de sa g\u00e9n\u00e9ration. Son nouveau film, \"Planetarium\" avec Natalie Portman et Lily-Rose Depp, est sorti en salle le 16 novembre 2016. Rebecca Zlotowski \u00e9voque avec Lauren Bastide\u00a0les \u00e9pisodes de sa vie et de sa carri\u00e8re qui ont fa\u00e7onn\u00e9 sa construction en tant que femme. Son enfance, la mort de sa m\u00e8re et sa pubert\u00e9 (05.36), son passage d'une agr\u00e9gation de lettres au m\u00e9tier de r\u00e9alisatrice (19:03), le sexisme dans le\u00a0cin\u00e9ma fran\u00e7ais (24:30), ses rapports avec L\u00e9a Seydoux et Lily-Rose Depp (29:22) et le caract\u00e8re forc\u00e9ment pr\u00e9dateur\u00a0du m\u00e9tier de metteur en sc\u00e8ne (33:36).\u00a0 La Poudre\u00a0est une production Nouvelles \u00c9coutes R\u00e9alisation et g\u00e9n\u00e9rique : Aurore Meyer-Mahieu. Mixage : Zaki Allal. Assistante de production : Zisla Tortello.\u00a0 ------ Cet \u00e9pisode 1 de La Poudre, enregistr\u00e9 \u00e0 l\u2019H\u00f4tel Providence, est rendu possible gr\u00e2ce au soutien des micros Blue Microphones. ------ vcfr3b5x See Privacy Policy at https://art19.com/privacy and California Privacy Notice at https://art19.com/privacy#do-not-sell-my-info.",
            "creator": "Lauren Bastide",
            "dc:creator": "Lauren Bastide",
            "enclosure": {
                "length": "47685705",
                "type": "audio/x-m4a",
                "url": "https://anchor.fm/s/6a2cdc64/podcast/play/39764475/https%3A%2F%2Fd3ctxlq1ktw2nl.cloudfront.net%2Fstaging%2F2021-10-19%2Fc5a09adaf3300def34e4604622e0aec5.m4a"
            },
            "guid": "70643a0c043f43c495d9a7baee8559df",
            "isoDate": "2016-12-01T01:00:00.000Z",
            "itunes": {
                "duration": "00:49:08",
                "episodeType": "full",
                "explicit": "No",
                "image": "https://d3t3ozftmdmh3i.cloudfront.net/staging/podcast_uploaded_episode400/17713249/0a90f2aaee28c96a.jpeg",
                "summary": "<p>La Poudre essaime depuis 6 saisons, et rec\u00e8le d\u2019interviews passionnantes avec des femmes artistes, militantes, politiques, d\u2019analyses men\u00e9es avec les plus grandes chercheur\u00b7euse\u00b7s contemporain\u00b7e\u00b7s en \u00e9tudes de genre, de tables rondes s\u2019attaquant au monde d\u2019aujourd\u2019hui et de documentaires \u00e9v\u00e9nementiels sur les luttes pour les droits des femmes. Si cet \u00e9pisode vous a plu, vous pourrez retrouver tous les (nombreux) autres sur Spotify !</p>\n<p>Dans ce tout premier \u00e9pisode de La Poudre, Rebecca Zlotowski se livre au micro de Lauren Bastide (@LaurenBastide), dans l\u2019intimit\u00e9 d'une chambre d\u2019h\u00f4tel. R\u00e9compens\u00e9e du Prix Louis-Delluc du premier film pour&nbsp;\"Belle Epine\" (2011) puis du Prix Fran\u00e7ois Chalais dans la s\u00e9lection Un Certain Regard au&nbsp;Festival de Cannes pour \"Grand Central\" (2013), avec L\u00e9a Seydoux en t\u00eate d'affiche,&nbsp;Rebecca Zlotowski est consid\u00e9r\u00e9e comme l'une des r\u00e9alisatrices les plus talentueuses de sa g\u00e9n\u00e9ration. Son nouveau film, \"Planetarium\" avec Natalie Portman et Lily-Rose Depp, est sorti en salle le 16 novembre 2016. Rebecca Zlotowski \u00e9voque avec Lauren Bastide&nbsp;les \u00e9pisodes de sa vie et de sa carri\u00e8re qui ont fa\u00e7onn\u00e9 sa construction en tant que femme. Son enfance, la mort de sa m\u00e8re et sa pubert\u00e9 (05.36), son passage d'une agr\u00e9gation de lettres au m\u00e9tier de r\u00e9alisatrice (19:03), le sexisme dans le&nbsp;cin\u00e9ma fran\u00e7ais (24:30), ses rapports avec L\u00e9a Seydoux et Lily-Rose Depp (29:22) et le caract\u00e8re forc\u00e9ment pr\u00e9dateur&nbsp;du m\u00e9tier de metteur en sc\u00e8ne (33:36).&nbsp; La Poudre&nbsp;est une production Nouvelles \u00c9coutes R\u00e9alisation et g\u00e9n\u00e9rique : Aurore Meyer-Mahieu. Mixage : Zaki Allal. Assistante de production : Zisla Tortello.&nbsp; ------ Cet \u00e9pisode 1 de La Poudre, enregistr\u00e9 \u00e0 l\u2019H\u00f4tel Providence, est rendu possible gr\u00e2ce au soutien des micros Blue Microphones. ------ vcfr3b5x See Privacy Policy at https://art19.com/privacy and California Privacy Notice at https://art19.com/privacy#do-not-sell-my-info.</p>\n"
            },
            "link": "https://podcasters.spotify.com/pod/show/lauren-bastide/episodes/pisode-1---Rebecca-Zlotowski-e16s11r",
            "pubDate": "Thu, 01 Dec 2016 01:00:00 GMT",
            "title": "\u00c9pisode 1 - Rebecca Zlotowski",
            "entities": {
                "CARDINAL": [
                    "6"
                ],
                "PERSON": [
                    "Si cet \u00e9pisode",
                    "Rebecca Zlotowski",
                    "Prix Louis-Delluc",
                    "L\u00e9a Seydoux",
                    "Rebecca Zlotowski",
                    "consid\u00e9r\u00e9e comme",
                    "nouveau",
                    "Natalie Portman",
                    "Rebecca Zlotowski",
                    "Lauren Bastide",
                    "qui ont fa\u00e7onn\u00e9 sa",
                    "la mort de sa",
                    "L\u00e9a Seydoux",
                    "La Poudre",
                    "Aurore Meyer-Mahieu",
                    "Zaki Allal",
                    "Zisla Tortello"
                ],
                "FAC": [
                    "Spotify"
                ],
                "NORP": [
                    "Dans",
                    "dans",
                    "dans"
                ],
                "ORG": [
                    "d\u2019h\u00f4tel",
                    "de sa",
                    "de sa",
                    "enregistr\u00e9 \u00e0 l\u2019H\u00f4tel Providence",
                    "gr\u00e2ce",
                    "soutien des micros Blue Microphones"
                ],
                "DATE": [
                    "2011",
                    "2013"
                ],
                "PRODUCT": [
                    "Un"
                ],
                "WORK_OF_ART": [
                    "Grand Central",
                    "Nouvelles \u00c9coutes R\u00e9alisation et g\u00e9n\u00e9rique :"
                ],
                "TIME": [
                    "16 novembre 2016",
                    "19:03",
                    "24:30"
                ],
                "GPE": [
                    "California"
                ]
            }
        },
        {
            "content": "<p>Le premier \u00e9pisode de La Poudre sera en ligne le 1er d\u00e9cembre. Apr\u00e8s \u00e7a, Lauren Bastide reviendra un jeudi sur deux avec un nouvel \u00e9pisode. La Poudre est une \u00e9mission de conversation avec les femmes qui fa\u00e7onnent le 21\u00e8me si\u00e8cle. Dans cette bande-annonce inaugurale, un avant go\u00fbt de ce qui vous attend.&nbsp;</p>\n",
            "contentSnippet": "Le premier \u00e9pisode de La Poudre sera en ligne le 1er d\u00e9cembre. Apr\u00e8s \u00e7a, Lauren Bastide reviendra un jeudi sur deux avec un nouvel \u00e9pisode. La Poudre est une \u00e9mission de conversation avec les femmes qui fa\u00e7onnent le 21\u00e8me si\u00e8cle. Dans cette bande-annonce inaugurale, un avant go\u00fbt de ce qui vous attend.",
            "creator": "Lauren Bastide",
            "dc:creator": "Lauren Bastide",
            "enclosure": {
                "length": "3868330",
                "type": "audio/x-m4a",
                "url": "https://anchor.fm/s/6a2cdc64/podcast/play/39764437/https%3A%2F%2Fd3ctxlq1ktw2nl.cloudfront.net%2Fstaging%2F2021-10-20%2F02c068c2823b623103685832c3e6430c.m4a"
            },
            "guid": "f59053af8847e645839d05967c3ad476",
            "isoDate": "2016-11-03T17:42:11.000Z",
            "itunes": {
                "duration": "00:03:59",
                "episodeType": "full",
                "explicit": "No",
                "image": "https://d3t3ozftmdmh3i.cloudfront.net/staging/podcast_uploaded_episode400/17713249/af641da66b25cc1f.jpeg",
                "summary": "<p>Le premier \u00e9pisode de La Poudre sera en ligne le 1er d\u00e9cembre. Apr\u00e8s \u00e7a, Lauren Bastide reviendra un jeudi sur deux avec un nouvel \u00e9pisode. La Poudre est une \u00e9mission de conversation avec les femmes qui fa\u00e7onnent le 21\u00e8me si\u00e8cle. Dans cette bande-annonce inaugurale, un avant go\u00fbt de ce qui vous attend.&nbsp;</p>\n"
            },
            "link": "https://podcasters.spotify.com/pod/show/lauren-bastide/episodes/Bande-annonce-e16s10l",
            "pubDate": "Thu, 03 Nov 2016 17:42:11 GMT",
            "title": "Bande-annonce",
            "entities": {
                "ORDINAL": [
                    "1er"
                ],
                "PERSON": [
                    "Lauren Bastide",
                    "go\u00fbt de ce qui vous"
                ],
                "ORG": [
                    "un",
                    "un",
                    "un"
                ],
                "CARDINAL": [
                    "21\u00e8me"
                ],
                "NORP": [
                    "Dans"
                ]
            }
        }
    ],
    "itunes": {
        "author": "Lauren Bastide",
        "categories": [
            "Society & Culture"
        ],
        "categoriesWithSubs": [
            {
                "name": "Society & Culture",
                "subs": null
            }
        ],
        "explicit": "No",
        "image": "https://d3t3ozftmdmh3i.cloudfront.net/production/podcast_uploaded_nologo/17713249/17713249-1632211174146-8cc0954b36cf3.jpg",
        "owner": {
            "email": "lapoudre@nouvellesecoutes.fr",
            "name": "Lauren Bastide"
        },
        "summary": "<p>Deux fois par mois, au micro de Lauren Bastide, \u00e9crivaines, artistes, chercheuses et militantes se racontent et prennent le pouls des luttes f\u00e9ministes et antiracistes contemporaines.\u00a0</p><p>Depuis 2016, la journaliste re\u00e7oit dans La Poudre des femmes artistes, militantes ou politiques pour des conversations intimes et profondes qui ont passionn\u00e9 de millions d\u2019auditeurices. Ces r\u00e9cits, enrichis de documentaires \u00e9v\u00e9nementiels, de tables rondes, et d\u2019analyses par les plus grandes expertes des luttes pour les droits des femmes, en France et dans le monde, forment un tableau captivant de la soci\u00e9t\u00e9 \u00e0 l\u2019heure de la r\u00e9volution #MeToo.\u00a0</p><p>La Poudre was created by journalist and feminist activist Lauren Bastide, co-founder of Nouvelles Ecoutes studio, to offer women a safe space to express themselves. In a one-hour long, in-depth conversation, inspirational women artists, activists, scientists and politics talk about themselves, their path and struggles, but also about the incredible times we are living for women\u2019s rights. Many episodes of La Poudre have been recorded or dubbed into English. Search for the \ud83c\uddec\ud83c\udde7 !</p>"
    },
    "language": "fr-fr",
    "lastBuildDate": "Tue, 16 May 2023 06:12:18 GMT",
    "link": "https://podcasters.spotify.com/pod/show/lauren-bastide",
    "paginationLinks": {
        "self": "https://anchor.fm/s/6a2cdc64/podcast/rss"
    },
    "palette": [
        "0E1413",
        "FBD3C3",
        "9B8982",
        "7C645E",
        "7D6C5C",
        "BC948C"
    ],
    "title": "La Poudre",
    "entities": {
        "PERSON": [
            "Depuis 2016",
            "dans La Poudre",
            "qui ont passionn\u00e9",
            "La Poudre",
            "Lauren Bastide"
        ],
        "GPE": [
            "la",
            "France"
        ],
        "NORP": [
            "dans"
        ],
        "ORG": [
            "un",
            "de la",
            "Nouvelles Ecoutes",
            "La Poudre"
        ],
        "TIME": [
            "one-hour"
        ],
        "LANGUAGE": [
            "English"
        ]
    }
}